deeptrade/__init__.py
deeptrade/sentiment.py
deeptrade/stocks.py
deeptrade-0.0.5.dist-info/LICENSE
deeptrade-0.0.5.dist-info/METADATA
deeptrade-0.0.5.dist-info/WHEEL
deeptrade-0.0.5.dist-info/top_level.txt
deeptrade-0.0.5.dist-info/RECORD
